aiomessaging/__init__.py
aiomessaging/app.py
aiomessaging/cluster.py
aiomessaging/config.py
aiomessaging/event.py
aiomessaging/exceptions.py
aiomessaging/logging.py
aiomessaging/message.py
aiomessaging/pipeline.py
aiomessaging/router.py
aiomessaging/utils.py
aiomessaging-0.2.dist-info/METADATA
aiomessaging-0.2.dist-info/RECORD
aiomessaging-0.2.dist-info/WHEEL
aiomessaging-0.2.dist-info/top_level.txt
