Metadata-Version: 2.1
Name: aiomessaging
Version: 0.2
Summary: Python asyncio messaging Framework
Home-page: https://github.com/aiomessaging/aiomessaging/
Author: Roman Tolkachyov
Author-email: roman@tolkachyov.name
License: UNKNOWN
Download-URL: https://github.com/aiomessaging/aiomessaging/archive/0.2.tar.gz
Keywords: asyncio,messaging,events,queues,email,delivery,sms,push
Platform: UNKNOWN
Classifier: Development Status :: 1 - Planning
Classifier: Framework :: AsyncIO
Classifier: Programming Language :: Python :: 3.6
Classifier: Programming Language :: Python :: 3.7
Classifier: Topic :: Internet
Classifier: Topic :: System :: Networking
Classifier: Topic :: Software Development :: Libraries
Classifier: Topic :: Communications :: Email
Classifier: Topic :: Communications :: Chat
Classifier: Topic :: Utilities
Classifier: License :: OSI Approved :: MIT License
Provides-Extra: dev
Requires-Dist: attrdict
Requires-Dist: ujson
Requires-Dist: pika
Requires-Dist: PyYAML
Requires-Dist: termcolor
Provides-Extra: dev
Requires-Dist: Sphinx; extra == 'dev'
Requires-Dist: commonmark; extra == 'dev'
